{
    "<URL>": "http://3.83.87.188/ghost",
    "<URL_3_4_2>": "https://ghost-nziq.onrender.com/ghost",
    "<URL_HOME>": "http://3.83.87.188",
    "<URL_HOME_3_4_2>": "https://ghost-nziq.onrender.com",
    "<GHOST_MAIL>": "user@example.com",
    "<GHOST_PASSWORD>": "r7aHWhKneSw=",
    "<GHOST_PASSWORD_NEW>": "r7aHWhKneSw=",
    "<GHOST_NAME>": "user",
    "<GHOST_NAME_NEW>": "user_ch_",
    "<GHOST_PRIVATE_PASSWORD>": "12345678",
    "<NEW_POST>": "NEW Post",
    "<NEW_LABEL>": "My new item",
    "<EDIT_LABEL>": "My new itemV2",
    "<NEW_DESC>": "Smile every day",
    "<NEW_TAG>": "NEW_TAG"
  }
